aws_toolkit-1.0.1.dist-info/DESCRIPTION.rst
aws_toolkit-1.0.1.dist-info/METADATA
aws_toolkit-1.0.1.dist-info/RECORD
aws_toolkit-1.0.1.dist-info/WHEEL
aws_toolkit-1.0.1.dist-info/metadata.json
aws_toolkit-1.0.1.dist-info/top_level.txt
awspackage/__init__.py
awspackage/aws.py
awspackage/network.py
