Metadata-Version: 2.0
Name: aws-toolkit
Version: 1.0.1
Summary: An AWS Provisioning Tool
Home-page: https://github.com/cjaiwenwen/aws
Author: Chen Jun
Author-email: cjaiwenwen@gmail.com
License: MIT
Platform: UNKNOWN
Requires-Dist: IPy
Requires-Dist: boto3
Requires-Dist: paramiko
Requires-Dist: prettytable
